clit/__init__.py
clit/clit.py
clit-0.0.1.data/scripts/hello-clit
clit-0.0.1.dist-info/METADATA
clit-0.0.1.dist-info/RECORD
clit-0.0.1.dist-info/WHEEL
clit-0.0.1.dist-info/entry_points.txt
clit-0.0.1.dist-info/top_level.txt
