Metadata-Version: 2.1
Name: clit
Version: 0.0.1
Summary: clit - Command LIne Toolkit
Home-page: UNKNOWN
Author: 
Author-email: 
License: MIT
Platform: UNKNOWN
Provides-Extra: dev
Provides-Extra: dev
Requires-Dist: pytest; extra == 'dev'
Requires-Dist: tox; extra == 'dev'
